{
  "$schema": "https://developer.microsoft.com/json-schemas/fabric/item/report/definition/visualContainer/2.10.0/schema.json",
  "name": "ov_insights",
  "position": {
    "x": 15.756294684488653,
    "y": 640.27852036058437,
    "z": 12000,
    "height": 80.213863848305877,
    "width": 1247.6120609263289,
    "tabOrder": 12000
  },
  "visual": {
    "visualType": "textbox",
    "objects": {
      "general": [
        {
          "properties": {
            "paragraphs": [
              {
                "textRuns": [
                  {
                    "value": "KEY INSIGHTS",
                    "textStyle": {
                      "fontWeight": "bold",
                      "fontFamily": "Segoe UI Semibold",
                      "fontSize": "12pt",
                      "color": "#1f6feb"
                    }
                  }
                ]
              },
              {
                "textRuns": [
                  {
                    "value": "$11.8bn revenue on 14.3M cargo tonnes at 82% on-time — yet load factor is just 15%: 93% of segments fly under half-full, the single biggest capacity opportunity. FedEx (FX) moves 43% of all freight (concentration risk). On-time is seasonal, peaking ~88% in October and softening to ~77% mid-year.",
                    "textStyle": {
                      "fontWeight": "bold",
                      "fontFamily": "Segoe UI",
                      "fontSize": "10.5pt",
                      "color": "#334155"
                    }
                  }
                ]
              }
            ]
          }
        }
      ]
    },
    "visualContainerObjects": {
      "title": [
        {
          "properties": {
            "show": {
              "expr": {
                "Literal": {
                  "Value": "false"
                }
              }
            }
          }
        }
      ],
      "background": [
        {
          "properties": {
            "show": {
              "expr": {
                "Literal": {
                  "Value": "true"
                }
              }
            },
            "color": {
              "solid": {
                "color": {
                  "expr": {
                    "Literal": {
                      "Value": "'#FFFFFF'"
                    }
                  }
                }
              }
            }
          }
        }
      ],
      "border": [
        {
          "properties": {
            "show": {
              "expr": {
                "Literal": {
                  "Value": "true"
                }
              }
            },
            "color": {
              "solid": {
                "color": {
                  "expr": {
                    "Literal": {
                      "Value": "'#E5E9F0'"
                    }
                  }
                }
              }
            }
          }
        }
      ]
    }
  }
}